crammit
