Metadata-Version: 1.1
Name: crammit
Version: 0.5
Summary: Asset packaging library. Concatenates, Minifies, and Compresses CSS and JavaScript
Home-page: https://github.com/rspivak/crammit.git
Author: Ruslan Spivak
Author-email: ruslan.spivak@gmail.com
License: MIT
Platform: UNKNOWN
Classifier: Intended Audience :: Developers
Classifier: License :: OSI Approved :: MIT License
Classifier: Programming Language :: Python
Classifier: Topic :: Utilities
Classifier: Operating System :: Unix
